[
  {
    "image": "/assets/images/post/image1.jpg",
    "heading": "Game Over",
    "sub-heading": "And When I wake up, you are still with me",
    "link": "/deployment-and-hosting"
  },
  {
    "image": "/assets/images/post/image2.jpg",
    "heading": "Two of Us",
    "sub-heading": ".. So I stole his last name.",
    "link": "/blog-configuration"
  },
  {
    "image": "/assets/images/post/image3.jpg",
    "heading": "Beach Baby pink",
    "sub-heading": ".. So I stole his last name.",
    "link": "/jekyll-theming"
  },
  {
    "image": "/assets/images/post/image4.jpg",
    "heading": "Top 10 Wedding Songs",
    "sub-heading": ".. Wrapping around.",
    "link": "/deployment-and-hosting"
  },
  {
    "image": "/assets/images/post/image5.jpg",
    "heading": "Say Hellow to Rajasthan",
    "sub-heading": ".. So I stole his last name.",
    "link": "/blog-configuration"
  },
]
